<pimpmykerberos.core.Core>
  <coreFile>./configFile/aCore.xml</coreFile>
  <webServerPort>443</webServerPort>
  <webSocketPort>4430</webSocketPort>
  <debug>true</debug>
  <timeBetweenScan>60000</timeBetweenScan>
  <debugJetty>false</debugJetty>
  <adminPassword>admin</adminPassword>
  <maxLogEntries>1000</maxLogEntries>
  <kerberosioPath>/kerberos</kerberosioPath>
  <maxDisplayLineInGUI>5</maxDisplayLineInGUI>
  <daysBeforePurge>30</daysBeforePurge>
  <maxDisplayColumnInGUI>6</maxDisplayColumnInGUI>
  <nightMode>0</nightMode>
  <muteMode>0</muteMode>
  <http2>true</http2>
  <sessionId>0</sessionId>
  <users>
    <entry>
      <string>admin</string>
      <pimpmykerberos.beans.User>
        <description>Administrator</description>
        <name>admin</name>
        <password>admin</password>
        <cameras>
          <entry>
            <string>camera1_name</string>
            <pimpmykerberos.beans.Camera>
              <name>camera1_name</name>
              <capturePath>/kerberos/camera1_name/capture</capturePath>
              <kerberosPort>81</kerberosPort>
              <daysBeforePurge>30</daysBeforePurge>
              <broadcastPort>8889</broadcastPort>
              <freshDate>2020-03-28 17:27:56.0 UTC</freshDate>
            </pimpmykerberos.beans.Camera>
          </entry>
          <entry>
            <string>camera4_name</string>
            <pimpmykerberos.beans.Camera>
              <name>camera4_name</name>
              <capturePath>/kerberos/camera4_name/capture</capturePath>
              <kerberosPort>84</kerberosPort>
              <daysBeforePurge>30</daysBeforePurge>
              <broadcastPort>8892</broadcastPort>
              <freshDate>2020-03-28 17:27:59.0 UTC</freshDate>
            </pimpmykerberos.beans.Camera>
          </entry>
          <entry>
            <string>camera3_name</string>
            <pimpmykerberos.beans.Camera>
              <name>camera3_name</name>
              <capturePath>/kerberos/camera3_name/capture</capturePath>
              <kerberosPort>83</kerberosPort>
              <daysBeforePurge>30</daysBeforePurge>
              <broadcastPort>8891</broadcastPort>
              <freshDate>2020-03-28 17:27:28.0 UTC</freshDate>
            </pimpmykerberos.beans.Camera>
          </entry>
          <entry>
            <string>camera2_name</string>
            <pimpmykerberos.beans.Camera>
              <name>camera2_name</name>
              <capturePath>/kerberos/camera2_name/capture</capturePath>
              <kerberosPort>82</kerberosPort>
              <daysBeforePurge>30</daysBeforePurge>
              <broadcastPort>8890</broadcastPort>
              <freshDate>2020-03-28 17:27:59.0 UTC</freshDate>
            </pimpmykerberos.beans.Camera>
          </entry>
        </cameras>
      </pimpmykerberos.beans.User>
    </entry>
  </users>
  <dataPath></dataPath>
  <influxDbUrl></influxDbUrl>
  <influxDbName>pimpMyKerberos</influxDbName>
  <influxDbUser>root</influxDbUser>
  <influxDbPasswd>root</influxDbPasswd>
  <paypal>https://paypal.me/FredericCOSTANT/2</paypal>
</pimpmykerberos.core.Core>